openetl_utils/__init__.py
openetl_utils/__init__.py.bak
openetl_utils/__migrations__/app.py
openetl_utils/__migrations__/batch.py
openetl_utils/__migrations__/scheduler.py
openetl_utils/cache.py
openetl_utils/celery_utils.py
openetl_utils/connector_utils.py
openetl_utils/database_utils.py
openetl_utils/enums.py
openetl_utils/local_connection_utils.py
openetl_utils/logger.py
openetl_utils/main_api_class.py
openetl_utils/main_db_class.py
openetl_utils/pipeline_utils.py
openetl_utils/scheduler_utils.py
openetl_utils/spark_utils.py
openetl_utils-0.1.5.dist-info/LICENSE
openetl_utils-0.1.5.dist-info/METADATA
openetl_utils-0.1.5.dist-info/WHEEL
openetl_utils-0.1.5.dist-info/RECORD
