Metadata-Version: 2.3
Name: openetl-utils
Version: 0.1.5
Summary: Simple ETL utilities used by OpenETL
License: MIT
Keywords: etl,data,utilities
Author: Rusab Khan
Author-email: rusabkhan7@gmail.com
Requires-Python: >=3.12
Classifier: Programming Language :: Python :: 3.12
Classifier: License :: OSI Approved :: MIT License
Classifier: Operating System :: OS Independent
Requires-Dist: SQLAlchemy (==2.0.36)
Requires-Dist: alembic (==1.14.0)
Requires-Dist: croniter (==5.0.1)
Requires-Dist: flatten-json (==0.1.14)
Requires-Dist: numpy (==2.1.3)
Requires-Dist: pandas (==2.2.3)
Requires-Dist: pyspark (==3.5.3)
Requires-Dist: regex (==2024.11.6)
Requires-Dist: requests (==2.32.3)
Project-URL: Documentation, https://rusabkhan.github.io/OpenETL/
Project-URL: Homepage, https://dataomnisolutions.com
Project-URL: Repository, https://github.com/RusabKhan/OpenETL
